huaweicloudsdkkms/__init__.py
huaweicloudsdkkms/v2/__init__.py
huaweicloudsdkkms/v2/kms_async_client.py
huaweicloudsdkkms/v2/kms_client.py
huaweicloudsdkkms/v2/model/__init__.py
huaweicloudsdkkms/v2/model/action_resources.py
huaweicloudsdkkms/v2/model/alias_entity.py
huaweicloudsdkkms/v2/model/api_link.py
huaweicloudsdkkms/v2/model/api_version_detail.py
huaweicloudsdkkms/v2/model/associate_alias_request.py
huaweicloudsdkkms/v2/model/associate_alias_request_body.py
huaweicloudsdkkms/v2/model/associate_alias_response.py
huaweicloudsdkkms/v2/model/batch_create_kms_tags_request.py
huaweicloudsdkkms/v2/model/batch_create_kms_tags_request_body.py
huaweicloudsdkkms/v2/model/batch_create_kms_tags_response.py
huaweicloudsdkkms/v2/model/cancel_grant_request.py
huaweicloudsdkkms/v2/model/cancel_grant_response.py
huaweicloudsdkkms/v2/model/cancel_key_deletion_request.py
huaweicloudsdkkms/v2/model/cancel_key_deletion_response.py
huaweicloudsdkkms/v2/model/cancel_self_grant_request.py
huaweicloudsdkkms/v2/model/cancel_self_grant_response.py
huaweicloudsdkkms/v2/model/create_alias_request.py
huaweicloudsdkkms/v2/model/create_alias_request_body.py
huaweicloudsdkkms/v2/model/create_alias_response.py
huaweicloudsdkkms/v2/model/create_datakey_request.py
huaweicloudsdkkms/v2/model/create_datakey_request_body.py
huaweicloudsdkkms/v2/model/create_datakey_response.py
huaweicloudsdkkms/v2/model/create_datakey_without_plaintext_request.py
huaweicloudsdkkms/v2/model/create_datakey_without_plaintext_response.py
huaweicloudsdkkms/v2/model/create_ec_datakey_pair_request.py
huaweicloudsdkkms/v2/model/create_ec_datakey_pair_request_body.py
huaweicloudsdkkms/v2/model/create_ec_datakey_pair_response.py
huaweicloudsdkkms/v2/model/create_grant_request.py
huaweicloudsdkkms/v2/model/create_grant_request_body.py
huaweicloudsdkkms/v2/model/create_grant_response.py
huaweicloudsdkkms/v2/model/create_key_request.py
huaweicloudsdkkms/v2/model/create_key_request_body.py
huaweicloudsdkkms-3.1.184.dist-info/METADATA
huaweicloudsdkkms-3.1.184.dist-info/WHEEL
huaweicloudsdkkms-3.1.184.dist-info/licenses/LICENSE
huaweicloudsdkkms-3.1.184.dist-info/RECORD
